{
  "1e3bff88-29b9-4b3f-be34-bffc38624bac": {
    "timed": false,
    "story ID": "1e3bff88-29b9-4b3f-be34-bffc38624bac",
    "title": {
      "con-Latn-EC": "103 Singo a'i",
      "en": "Black People",
      "es": "El negro",
      "_default": "Singo a'i"
    },
    "media": {
      "audio": "",
      "video": ""
    },
    "languages": [
      "con-Latn-EC",
      "en",
      "es"
    ],
    "date_created": "",
    "date_uploaded": "2/3/2018",
    "source": {
      "con-Latn-EC": "Blaser, Magdalena \"Mitos del pueblo Cofán\"",
      "en": "Blaser, Magdalena \"Myths of the Cofán people\"",
      "_default": ""
    },
    "description": "",
    "genre": "",
    "author": "",
    "glosser": "",
    "speakers": [],
    "xml_file_name": "103.xml",
    "source_filetype": "FLEx",
    "tier IDs": {
      "palabra en a'ingae (ortografía Borman)": {
        "subdivided": true
      },
      "morfema (como en el texto) en a'ingae (ortografía Borman)": {
        "subdivided": true
      },
      "morfema (forma típica) en a'ingae (ortografía Borman)": {
        "subdivided": true
      },
      "glosa de morfema en inglés": {
        "subdivided": true
      },
      "frase en inglés": {
        "subdivided": false
      },
      "frase en Español": {
        "subdivided": false
      },
      "frase en a'ingae (ortografía Borman)": {
        "subdivided": false
      }
    }
  },
  "1ed3d641-acd9-4466-811d-17c8ed59844c": {
    "timed": true,
    "story ID": "1ed3d641-acd9-4466-811d-17c8ed59844c",
    "title": {
      "_default": "Kuke chiste"
    },
    "media": {
      "audio": "20170804_kuke_chiste_FACQ.mp3",
      "video": "20170804_kuke_chiste_FACQ_handbrake.mp4"
    },
    "languages": [],
    "date_created": "",
    "date_uploaded": "8/30/2018",
    "source": {
      "_default": ""
    },
    "description": "A joke about a hare\n",
    "genre": "",
    "author": "",
    "glosser": "",
    "speakers": [
      "Fausto Criollo"
    ],
    "xml_file_name": "20170804_kuke_chiste_FACQ.eaf",
    "source_filetype": "ELAN",
    "tier IDs": {
      "Gloss": {
        "subdivided": true
      },
      "Glosa": {
        "subdivided": true
      },
      "Ortografía vieja": {
        "subdivided": true
      },
      "Morfema": {
        "subdivided": true
      },
      "English": {
        "subdivided": true
      },
      "Español": {
        "subdivided": true
      },
      "A'ingae": {
        "subdivided": true
      }
    },
    "speaker IDs": {
      "S1": {
        "name": "Fausto Criollo",
        "tier": "--"
      }
    }
  },
  "71f939d8-3ec0-46cd-ab2d-0ae62904b37e": {
    "timed": true,
    "story ID": "71f939d8-3ec0-46cd-ab2d-0ae62904b37e",
    "title": {
      "_default": "MR-narracion"
    },
    "media": {
      "audio_local": "",
      "audio_remote": "",
      "video": "",
      "audio": "https://enenlhetaudio.nyc3.cdn.digitaloceanspaces.com/2019-08-16-MR-narracion.wav"
    },
    "languages": [],
    "date_created": "",
    "date_uploaded": "8/21/2025",
    "source": {
      "_default": ""
    },
    "description": "",
    "genre": "",
    "author": "",
    "glosser": "",
    "speakers": [
      "MR",
      "RH"
    ],
    "xml_file_name": "MR-narracion.eaf",
    "source_filetype": "ELAN",
    "tier IDs": {
      "transcript_MR": {
        "subdivided": false
      },
      "translation_MR": {
        "subdivided": false
      },
      "transcript_RH": {
        "subdivided": false
      }
    },
    "speaker IDs": {
      "S1": {
        "name": "MR",
        "tier": "transcript_MR"
      },
      "S2": {
        "name": "RH",
        "tier": "transcript_RH"
      }
    }
  }
}